TalkParser/__init__.py
TalkParser-0.0.0.dist-info/METADATA
TalkParser-0.0.0.dist-info/WHEEL
TalkParser-0.0.0.dist-info/top_level.txt
TalkParser-0.0.0.dist-info/RECORD
